paymouse/__init__.py
paymouse-0.1.dist-info/METADATA
paymouse-0.1.dist-info/RECORD
paymouse-0.1.dist-info/WHEEL
paymouse-0.1.dist-info/top_level.txt
