Metadata-Version: 2.1
Name: paymouse
Version: 0.1
Summary: Python multiple payment gateway
Home-page: https://github.com/markypython/paymouse
Author: Mark Skelton
Author-email: mdskelton99@gmail.com
License: MIT
Keywords: payments
Platform: UNKNOWN
Requires-Dist: stripe
Requires-Dist: authorizenet
